{"('base_model.model.model.layers.13.self_attn.o_proj', 14)": [0.69, 0.58], "('base_model.model.model.layers.10.self_attn.o_proj', 3)": [0.23, 0.15], "('base_model.model.model.layers.9.self_attn.o_proj', 2)": [0.17, 0.15], "('base_model.model.model.layers.9.self_attn.o_proj', 7)": [0.15, 0.15], "('base_model.model.model.layers.11.self_attn.o_proj', 23)": [0.3, 0.23], "('base_model.model.model.layers.6.self_attn.o_proj', 10)": [0.48, 0.39], "('base_model.model.model.layers.11.self_attn.o_proj', 24)": [0.15, 0.15], "('base_model.model.model.layers.9.self_attn.o_proj', 10)": [0.15, 0.15], "('base_model.model.model.layers.1.self_attn.o_proj', 9)": [0.17, 0.17], "('base_model.model.model.layers.7.self_attn.o_proj', 17)": [0.17, 0.15], "('base_model.model.model.layers.10.self_attn.o_proj', 7)": [0.57, 0.58], "('base_model.model.model.layers.5.self_attn.o_proj', 7)": [0.58, 0.58], "('base_model.model.model.layers.13.self_attn.o_proj', 0)": [0.16, 0.16], "('base_model.model.model.layers.12.self_attn.o_proj', 0)": [0.15, 0.15], "('base_model.model.model.layers.13.self_attn.o_proj', 12)": [0.15, 0.15], "('base_model.model.model.layers.12.self_attn.o_proj', 23)": [0.49, 0.47], "('base_model.model.model.layers.12.self_attn.o_proj', 9)": [0.15, 0.15], "('base_model.model.model.layers.9.self_attn.o_proj', 21)": [0.61, 0.42], "('base_model.model.model.layers.10.self_attn.o_proj', 4)": [0.45, 0.46], "('base_model.model.model.layers.4.self_attn.o_proj', 4)": [0.15, 0.15], "('base_model.model.model.layers.12.self_attn.o_proj', 8)": [0.15, 0.15], "('base_model.model.model.layers.8.self_attn.o_proj', 1)": [0.46, 0.4], "('base_model.model.model.layers.11.self_attn.o_proj', 2)": [0.64, 0.64], "('base_model.model.model.layers.13.self_attn.o_proj', 25)": [0.43, 0.43], "('base_model.model.model.layers.7.self_attn.o_proj', 26)": [0.15, 0.15], "('base_model.model.model.layers.9.self_attn.o_proj', 29)": [0.61, 0.6], "('base_model.model.model.layers.12.self_attn.o_proj', 5)": [0.15, 0.15], "('base_model.model.model.layers.12.self_attn.o_proj', 20)": [0.15, 0.15], "('base_model.model.model.layers.12.self_attn.o_proj', 16)": [0.65, 0.65], "('base_model.model.model.layers.11.self_attn.o_proj', 7)": [0.7, 0.7], "('base_model.model.model.layers.13.self_attn.o_proj', 4)": [0.21, 0.21], "('base_model.model.model.layers.6.self_attn.o_proj', 23)": [0.15, 0.15], "('base_model.model.model.layers.11.self_attn.o_proj', 9)": [0.45, 0.43], "('base_model.model.model.layers.11.self_attn.o_proj', 28)": [0.67, 0.66], "('base_model.model.model.layers.4.self_attn.o_proj', 27)": [0.58, 0.51]}